[
  {
    "id": "I_kwDOLrzjj86w6Ur7",
    "title": "愚人节笑话",
    "url": "https://github.com/zkl2333/vme/issues/138",
    "body": "哥，3号了，她还是没理你，压根没人在意你到底是讲愚人节笑话还是真的想表白，要不你把那五十二块发我吧，我想吃KFC",
    "createdAt": "2025-04-03T02:39:03Z",
    "updatedAt": "2025-04-03T02:40:47Z",
    "author": {
      "username": "zkl2333",
      "avatarUrl": "https://avatars.githubusercontent.com/u/18900961?u=da4ad19a3d0cd8a9d03c233b1120779f963494a5&v=4",
      "url": "https://github.com/zkl2333"
    }
  },
  {
    "id": "I_kwDOLrzjj86y5Lvy",
    "title": "欠款书",
    "url": "https://github.com/zkl2333/vme/issues/141",
    "body": "欠款书:\n            今天所有人都欠我50，什么原因自己想，有心者不用教，无心者教不会。　　--2025.4月17号星期四",
    "createdAt": "2025-04-17T03:49:25Z",
    "updatedAt": "2025-04-17T03:49:50Z",
    "author": {
      "username": "zkl2333",
      "avatarUrl": "https://avatars.githubusercontent.com/u/18900961?u=da4ad19a3d0cd8a9d03c233b1120779f963494a5&v=4",
      "url": "https://github.com/zkl2333"
    }
  }
]